quisp_widget/__init__.py
quisp_widget/_frontend.py
quisp_widget/_version.py
quisp_widget/channel.py
quisp_widget/network.py
quisp_widget/qnode.py
quisp_widget/types.py
quisp_widget/widget.py
quisp_widget/labextension/build_log.json
quisp_widget/labextension/package.json
quisp_widget/labextension/static/lib_index_js.16adeb1947d5ac72e5a4.js
quisp_widget/labextension/static/lib_index_js.16adeb1947d5ac72e5a4.js.map
quisp_widget/labextension/static/lib_plugin_js.d7dd6a908b8b64031c76.js
quisp_widget/labextension/static/lib_plugin_js.d7dd6a908b8b64031c76.js.map
quisp_widget/labextension/static/lib_widget_js.83af66c23eea6cbffbf2.js
quisp_widget/labextension/static/lib_widget_js.83af66c23eea6cbffbf2.js.map
quisp_widget/labextension/static/remoteEntry.3da8fc3edffb29e94c38.js
quisp_widget/labextension/static/remoteEntry.3da8fc3edffb29e94c38.js.map
quisp_widget/labextension/static/style.js
quisp_widget/nbextension/extension.js
quisp_widget/nbextension/index.js
quisp_widget/nbextension/index.js.map
quisp_widget/tests/__init__.py
quisp_widget/tests/conftest.py
quisp_widget/tests/test_nbextension_path.py
quisp_widget/tests/test_network.py
quisp_widget-0.1.0.dev1.data/data/share/jupyter/labextensions/quisp_widget/build_log.json
quisp_widget-0.1.0.dev1.data/data/share/jupyter/labextensions/quisp_widget/package.json
quisp_widget-0.1.0.dev1.data/data/share/jupyter/labextensions/quisp_widget/static/lib_index_js.16adeb1947d5ac72e5a4.js
quisp_widget-0.1.0.dev1.data/data/share/jupyter/labextensions/quisp_widget/static/lib_index_js.16adeb1947d5ac72e5a4.js.map
quisp_widget-0.1.0.dev1.data/data/share/jupyter/labextensions/quisp_widget/static/lib_plugin_js.d7dd6a908b8b64031c76.js
quisp_widget-0.1.0.dev1.data/data/share/jupyter/labextensions/quisp_widget/static/lib_plugin_js.d7dd6a908b8b64031c76.js.map
quisp_widget-0.1.0.dev1.data/data/share/jupyter/labextensions/quisp_widget/static/lib_widget_js.83af66c23eea6cbffbf2.js
quisp_widget-0.1.0.dev1.dist-info/METADATA
quisp_widget-0.1.0.dev1.dist-info/WHEEL
quisp_widget-0.1.0.dev1.dist-info/licenses/LICENSE.txt
quisp_widget-0.1.0.dev1.dist-info/RECORD
